[
  {
    "titreSousCycle": "Les films",
    "items": [
      {
        "titre": "Duelle",
        "idFilm": 46611,
        "idCycle": 152,
        "idCategorie": 1857,
        "realisateurs": "Jacques Rivette",
        "annee": 1975,
        "pays": "France",
        "textes": [
          {
            "typeTexte": 9,
            "texte": "Deux déesses, Leni, fille de la Lune, et Viva, fille du Soleil, passent sur la Terre quelques jours par an... Des humains, Lucie, jeune réceptionniste d'hôtel, Pierrot, acrobate, Jeanne/Elsa, ticket-girl dans un dancing, sont victimes de leurs jeux cruels."
          },
          {
            "typeTexte": 99,
            "texte": "Séance en présence de Pacôme Thiellement"
          }
        ],
        "generique": "Juliet Berto, Bulle Ogier, Jean Babilée, Hermine Karagheuz",
        "seance": [
          {
            "idFilm": 46611,
            "ordre": 1,
            "idSeance": 29337,
            "idCopie": 17735,
            "duree": 120,
            "version": "VOSTF",
            "format": "DCP",
            "idCycle": 152,
            "idCategorie": 1857,
            "idEvenement": 18774,
            "dateHeure": "2019-05-23T19:00:00",
            "idSalle": [
              "GF",
              "Georges Franju"
            ]
          }
        ]
      },
      {
        "titre": "Onibaba",
        "idFilm": 38096,
        "idCycle": 152,
        "idCategorie": 1857,
        "realisateurs": "Kaneto Shindo",
        "annee": 1965,
        "pays": "Japon",
        "textes": [
          {
            "typeTexte": 9,
            "texte": "Au XIVème siècle, au Japon, la guerre entre les samouraïs ruine le pays. Une femme et sa belle-fille subsistent difficilement en vendant les armes des soldats qu'elles ont tués. Un jour, apprenant que sa bru a une liaison avec un déserteur, la belle-mère se déguise en démon pour la terrifier."
          },
          {
            "typeTexte": 99,
            "texte": "Séance en présence d'Elina Löwensohn"
          }
        ],
        "generique": "Nobuko Otowa, Jitsuko Yoshimura, Kei Satô, Jûkichi Uno",
        "seance": [
          {
            "idFilm": 38096,
            "ordre": 1,
            "idSeance": 29294,
            "idCopie": 2366,
            "duree": 103,
            "version": "VOSTF",
            "format": "35 mm",
            "idCycle": 152,
            "idCategorie": 1857,
            "idEvenement": 18766,
            "dateHeure": "2019-05-16T19:00:00",
            "idSalle": [
              "GF",
              "Georges Franju"
            ]
          }
        ]
      },
      {
        "titre": "Prédateurs",
        "art": "Les",
        "titreVo": "Hunger",
        "artVo": "The",
        "idFilm": 36659,
        "idCycle": 152,
        "idCategorie": 1857,
        "realisateurs": "Tony Scott",
        "annee": 1982,
        "pays": "Grande-Bretagne",
        "textes": [
          {
            "typeTexte": 9,
            "texte": "Miriam, une femme vampire, vit à New York depuis trois cents ans, avec John. Celui-ci est soudainement frappé d'un processus accéléré de vieillissement. Sa compagne va tout tenter pour empêcher ce processus de dégradation."
          }
        ],
        "generique": "Catherine Deneuve, David Bowie, Susan Sarandon, Cliff De Young",
        "adaptation": "D'après le roman _Les Sanguinaires_ de Whitley Strieber.",
        "seance": [
          {
            "idFilm": 36659,
            "ordre": 2,
            "idSeance": 29436,
            "idCopie": 17734,
            "duree": 97,
            "version": "VOSTF",
            "format": "35 mm",
            "idCycle": 152,
            "idCategorie": 1857,
            "idEvenement": 18773,
            "dateHeure": "2019-05-09T19:00:00",
            "idSalle": [
              "GF",
              "Georges Franju"
            ]
          }
        ]
      },
      {
        "titre": "Satyricon",
        "titreVo": "Fellini Satyricon",
        "idFilm": 43358,
        "idCycle": 152,
        "idCategorie": 1857,
        "realisateurs": "Federico Fellini",
        "annee": 1969,
        "pays": "Italie-France",
        "textes": [
          {
            "typeTexte": 9,
            "texte": "Dans la Rome antique, Encolpe et Ascylte, deux étudiants du quartier souterrain de Subure où ils vivent de rapines, se disputent les faveurs de leur jeune esclave, Giton. Les trois comparses, tour à tour désunis et réunis, vivent différentes histoires au gré de leurs rencontres."
          },
          {
            "typeTexte": 99,
            "texte": "Séance en présence de Blutch"
          }
        ],
        "generique": "Martin Potter, Hiram Keller, Max Born, Luigi Fanfulla",
        "seance": [
          {
            "idFilm": 43358,
            "ordre": 1,
            "idSeance": 29822,
            "idCopie": 16653,
            "duree": 138,
            "version": "VOSTA",
            "format": "35 mm",
            "idCycle": 152,
            "idCategorie": 1857,
            "idEvenement": 18775,
            "dateHeure": "2019-04-25T19:00:00",
            "idSalle": [
              "HL",
              "Henri Langlois"
            ]
          }
        ]
      },
      {
        "titre": "Strangulation blues",
        "idFilm": 66323,
        "idCycle": 152,
        "idCategorie": 1857,
        "realisateurs": "Leos Carax",
        "annee": 1979,
        "pays": "France",
        "textes": [
          {
            "typeTexte": 9,
            "texte": "Au cours d'une nuit parisienne, Paul joue à étrangler Colette. Au petit matin, il prend la fuite."
          }
        ],
        "generique": "Eric Frey, Hans Meyer, Anne Petit-Lagrange",
        "seance": [
          {
            "idFilm": 66323,
            "ordre": 1,
            "idSeance": 29436,
            "idCopie": 17971,
            "duree": 16,
            "version": "",
            "format": "DCP",
            "idCycle": 152,
            "idCategorie": 1857,
            "idEvenement": 18773,
            "dateHeure": "2019-05-09T19:00:00",
            "idSalle": [
              "GF",
              "Georges Franju"
            ]
          }
        ]
      }
    ]
  }
]